hotfuzz/__init__.py
hotfuzz/fuzz.py
hotfuzz/hot.py
hotfuzz/hotfuzz.py
hotfuzz/item.py
hotfuzz/mode.py
hotfuzz/window.py
hotfuzz-0.2.0.dist-info/WHEEL
hotfuzz-0.2.0.dist-info/METADATA
hotfuzz-0.2.0.dist-info/RECORD
