Metadata-Version: 2.1
Name: hotfuzz
Version: 0.2.0
Summary: 
Author: megahomyak
Author-email: g.megahomyak@gmail.com
Requires-Python: >=3.8,<4.0
Classifier: Programming Language :: Python :: 3
Classifier: Programming Language :: Python :: 3.10
Classifier: Programming Language :: Python :: 3.8
Classifier: Programming Language :: Python :: 3.9
Requires-Dist: PyQt6 (>=6.5.2,<7.0.0)
Requires-Dist: fuzzyfinder (>=2.1.0,<3.0.0)
